noix/__init__.py
noix/nut.py
noix/telnet.py
noix-1.0.0.dist-info/METADATA
noix-1.0.0.dist-info/WHEEL
noix-1.0.0.dist-info/licenses/LICENSE.txt
noix-1.0.0.dist-info/RECORD
