Metadata-Version: 2.4
Name: noix
Version: 1.0.0
Summary: A NUT client for Python 3.13+
License: EUPL-1.2
License-File: LICENSE.txt
Author: Deuchnord
Author-email: jerome@deuchnord.fr
Requires-Python: >=3.10
Classifier: License :: OSI Approved :: European Union Public Licence 1.2 (EUPL 1.2)
Classifier: Programming Language :: Python :: 3
Classifier: Programming Language :: Python :: 3.10
Classifier: Programming Language :: Python :: 3.11
Classifier: Programming Language :: Python :: 3.12
Classifier: Programming Language :: Python :: 3.13
Classifier: Programming Language :: Python :: 3.14
Requires-Dist: telnetlib3 (>=2.0.8,<3.0.0)
